{"id": "1562002166", "id_str": "1562002166", "url": "https://x.com/kellipaddon", "username": "kellipaddon", "displayname": "Kelli Paddon", "rawDescription": "Former BC MLA & Parliamentary Secretary for Gender Equity, community advocate, advisor, ally. Mom to incredible humans, and long time Chilliwack resident", "created": "2013-07-02 02:25:07+00:00", "followersCount": "1493", "friendsCount": "550", "statusesCount": "1368", "favouritesCount": "1219", "listedCount": "25", "mediaCount": "373", "location": "Chilliwack, British Columbia", "profileImageUrl": "https://pbs.twimg.com/profile_images/1848538386103209988/8pygquzQ_normal.jpg", "profileBannerUrl": "https://pbs.twimg.com/profile_banners/1562002166/1732383722", "protected": "None", "verified": "False", "blue": "False", "blueType": "None", "descriptionLinks": [], "pinnedIds": "[]", "_type": "snscrape.modules.twitter.User"}