{"id": "219207028", "id_str": "219207028", "url": "https://x.com/Mike_de_Jong", "username": "Mike_de_Jong", "displayname": "Mike de Jong", "rawDescription": "Candidate for the Conservative nomination for Abbotsford - South Langley.  Hockey Fan, and Proud British Columbian.", "created": "2010-11-24 06:35:16+00:00", "followersCount": "7876", "friendsCount": "2412", "statusesCount": "2444", "favouritesCount": "538", "listedCount": "217", "mediaCount": "378", "location": "British Columbia", "profileImageUrl": "https://pbs.twimg.com/profile_images/1780746178260295681/-2tS2M8x_normal.jpg", "profileBannerUrl": "https://pbs.twimg.com/profile_banners/219207028/1713397949", "protected": "None", "verified": "False", "blue": "True", "blueType": "None", "descriptionLinks": [{"url": "http://www.mikedejong.ca", "text": "mikedejong.ca", "tcourl": "https://t.co/EI3wOq5SY3"}], "pinnedIds": "[]", "_type": "snscrape.modules.twitter.User"}