{"id": "108315956", "id_str": "108315956", "url": "https://x.com/_kevindonovan", "username": "_kevindonovan", "displayname": "Kevin Donovan", "rawDescription": "Chief Investigative Reporter at Toronto Star, husband, dad, son. Author of The Billionaire Murders, The Dead Times mystery thriller and Secret Life", "created": "2010-01-25 15:10:05+00:00", "followersCount": "16075", "friendsCount": "614", "statusesCount": "4411", "favouritesCount": "92", "listedCount": "232", "mediaCount": "60", "location": "Toronto", "profileImageUrl": "https://pbs.twimg.com/profile_images/478721118199508993/3qgLb0_1_normal.jpeg", "profileBannerUrl": "https://pbs.twimg.com/profile_banners/108315956/1575237322", "protected": "None", "verified": "False", "blue": "False", "blueType": "None", "descriptionLinks": [{"url": "http://thestar.ca", "text": "thestar.ca", "tcourl": "https://t.co/S0vQ0AH6Cz"}], "pinnedIds": "[]", "_type": "snscrape.modules.twitter_api_client.User"}