{"id": "1123066144502550528", "id_str": "1123066144502550528", "url": "https://x.com/annarobertsmp", "username": "annarobertsmp", "displayname": "Anna Roberts MP", "rawDescription": "Member of Parliament for #KingVaughan | Shadow Minister for Seniors \ud83c\udde8\ud83c\udde6", "created": "2019-04-30 03:26:49+00:00", "followersCount": "3843", "friendsCount": "843", "statusesCount": "2085", "favouritesCount": "2357", "listedCount": "54", "mediaCount": "1188", "location": "", "profileImageUrl": "https://pbs.twimg.com/profile_images/1468652097583337475/KgVm9xqg_normal.jpg", "profileBannerUrl": "https://pbs.twimg.com/profile_banners/1123066144502550528/1643236034", "protected": "None", "verified": "False", "blue": "False", "blueType": "Government", "descriptionLinks": [{"url": "http://www.annarobertsmp.ca", "text": "annarobertsmp.ca", "tcourl": "https://t.co/auSEFVzLCP"}], "pinnedIds": "[]", "_type": "snscrape.modules.twitter_api_client.User"}