{"id": "470554313", "id_str": "470554313", "url": "https://x.com/BentArrowYEG", "username": "BentArrowYEG", "displayname": "Bent Arrow", "rawDescription": "The Bent Arrow Traditional Healing Society is committed to building on the strengths of Aboriginal children, youth and their families.", "created": "2012-01-21 22:04:01+00:00", "followersCount": "5034", "friendsCount": "2100", "statusesCount": "2808", "favouritesCount": "1091", "listedCount": "59", "mediaCount": "789", "location": "Edmonton, Alberta", "profileImageUrl": "https://pbs.twimg.com/profile_images/1758616086696595456/W0REOs1Q_normal.jpg", "profileBannerUrl": "https://pbs.twimg.com/profile_banners/470554313/1607034141", "protected": "None", "verified": "False", "blue": "False", "blueType": "None", "descriptionLinks": [{"url": "http://www.bentarrow.ca", "text": "bentarrow.ca", "tcourl": "https://t.co/RcY5OP9YM0"}], "pinnedIds": "[]", "_type": "snscrape.modules.twitter_api_client.User"}