{"id": "18157489", "id_str": "18157489", "url": "https://x.com/bobmackin", "username": "bobmackin", "displayname": "Bob Mackin", "rawDescription": "News, sports, business and politics journalist. Red Mittens & Red Ink: The Vancouver Olympics author. Also reporting via @theBreakerNews", "created": "2008-12-16 06:08:27+00:00", "followersCount": "13679", "friendsCount": "7960", "statusesCount": "114352", "favouritesCount": "2413", "listedCount": "487", "mediaCount": "13525", "location": "North Vancouver, Canada", "profileImageUrl": "https://pbs.twimg.com/profile_images/1107659989710102530/MtbGQrbd_normal.png", "profileBannerUrl": "https://pbs.twimg.com/profile_banners/18157489/1560665255", "protected": "None", "verified": "False", "blue": "False", "blueType": "None", "descriptionLinks": [], "pinnedIds": "[]", "_type": "snscrape.modules.twitter_api_client.User"}