{"id": "363710590", "id_str": "363710590", "url": "https://x.com/Bret_Sears", "username": "Bret_Sears", "displayname": "Bret \ud83c\udf41", "rawDescription": "Political Correctness Ruins Everything.\n\nIndividual Responsibility, Personal Freedom, Fairness, Respect.\n\n\ud83d\udc9c @SammieT26", "created": "2011-08-28 15:21:37+00:00", "followersCount": "82882", "friendsCount": "64754", "statusesCount": "94842", "favouritesCount": "189130", "listedCount": "188", "mediaCount": "4936", "location": "Saint John, New Brunswick", "profileImageUrl": "https://pbs.twimg.com/profile_images/1821715887612702720/JI54WtV4_normal.jpg", "profileBannerUrl": "https://pbs.twimg.com/profile_banners/363710590/1648473863", "protected": "None", "verified": "False", "blue": "True", "blueType": "None", "descriptionLinks": [], "pinnedIds": "[1881050600357662902]", "_type": "snscrape.modules.twitter_api_client.User"}