{"id": "1397353530864947205", "id_str": "1397353530864947205", "url": "https://x.com/BrianWongMLA", "username": "BrianWongMLA", "displayname": "Brian Wong", "rawDescription": "PC Candidate for Waverley - Fall River - Beaver Bank Building up Nova Scotia\u2b06\ufe0f", "created": "2021-05-26 00:47:10+00:00", "followersCount": "590", "friendsCount": "361", "statusesCount": "2892", "favouritesCount": "4310", "listedCount": "7", "mediaCount": "480", "location": "418 Windsor Junction Rd ", "profileImageUrl": "https://pbs.twimg.com/profile_images/1850603652261580800/L2ZkWDX4_normal.jpg", "profileBannerUrl": "https://pbs.twimg.com/profile_banners/1397353530864947205/1730053301", "protected": "None", "verified": "False", "blue": "False", "blueType": "None", "descriptionLinks": [], "pinnedIds": "[]", "_type": "snscrape.modules.twitter_api_client.User"}