{"id": "971197163756752896", "id_str": "971197163756752896", "url": "https://x.com/busi_global", "username": "busi_global", "displayname": "Busi Global", "rawDescription": "", "created": "2018-03-07 01:33:42+00:00", "followersCount": "529", "friendsCount": "466", "statusesCount": "2065", "favouritesCount": "5097", "listedCount": "1", "mediaCount": "206", "location": "Ontario, Canada", "profileImageUrl": "https://pbs.twimg.com/profile_images/1749474396555583495/em8D8PBD_normal.jpg", "profileBannerUrl": "None", "protected": "None", "verified": "False", "blue": "False", "blueType": "None", "descriptionLinks": [], "pinnedIds": "[]", "_type": "snscrape.modules.twitter_api_client.User"}