{"id": "36211088", "id_str": "36211088", "url": "https://x.com/CBCRaffy", "username": "CBCRaffy", "displayname": "Raffy Boudjikanian", "rawDescription": "Senior Reporter, @CBCPolitics Parliamentary Bureau (via Edmonton, Calgary, Montreal). raffy.boudjikanian@cbc.ca. DMs open. Author tweets: @Raffyauthor", "created": "2009-04-28 23:26:42+00:00", "followersCount": "11065", "friendsCount": "4737", "statusesCount": "26942", "favouritesCount": "17950", "listedCount": "178", "mediaCount": "2955", "location": "Ottawa, Ontario", "profileImageUrl": "https://pbs.twimg.com/profile_images/1443965101078454277/rzT61T-M_normal.jpg", "profileBannerUrl": "https://pbs.twimg.com/profile_banners/36211088/1632261931", "protected": "None", "verified": "False", "blue": "False", "blueType": "None", "descriptionLinks": [], "pinnedIds": "[]", "_type": "snscrape.modules.twitter_api_client.User"}