{"id": "20184582", "id_str": "20184582", "url": "https://x.com/CBCVancouver", "username": "CBCVancouver", "displayname": "CBC Vancouver", "rawDescription": "This account is inactive. For more of CBC Vancouver, visit our website or @cbcnewsbc.", "created": "2009-02-05 20:34:13+00:00", "followersCount": "291526", "friendsCount": "3932", "statusesCount": "69888", "favouritesCount": "13324", "listedCount": "2945", "mediaCount": "6224", "location": "Vancouver, British Columbia", "profileImageUrl": "https://pbs.twimg.com/profile_images/1063502960125083648/KV0yzJxe_normal.jpg", "profileBannerUrl": "https://pbs.twimg.com/profile_banners/20184582/1676999726", "protected": "None", "verified": "False", "blue": "False", "blueType": "None", "descriptionLinks": [{"url": "http://www.cbc.ca/bccommunity", "text": "cbc.ca/bccommunity", "tcourl": "https://t.co/AxQf3GwIfV"}], "pinnedIds": "[1648091521458249728]", "_type": "snscrape.modules.twitter_api_client.User"}