{"id": "249308298", "id_str": "249308298", "url": "https://x.com/cindyeharnett", "username": "cindyeharnett", "displayname": "cindy e harnett", "rawDescription": "Times Colonist reporter covering health, federal politics. Mother of toddler covering tea parties & play dates. \r\nTweets my own; RTs & follows not endorsements.", "created": "2011-02-08 19:52:56+00:00", "followersCount": "2449", "friendsCount": "2300", "statusesCount": "8245", "favouritesCount": "7655", "listedCount": "97", "mediaCount": "226", "location": "", "profileImageUrl": "https://pbs.twimg.com/profile_images/1238849008/cindyharnett-small_normal.jpg", "profileBannerUrl": "None", "protected": "None", "verified": "False", "blue": "False", "blueType": "None", "descriptionLinks": [{"url": "http://timescolonist.com", "text": "timescolonist.com", "tcourl": "http://t.co/iX8bOA3LVn"}], "pinnedIds": "[]", "_type": "snscrape.modules.twitter_api_client.User"}