{"id": "19240249", "id_str": "19240249", "url": "https://x.com/CKNW", "username": "CKNW", "displayname": "CKNW", "rawDescription": "730 CKNW coming February 24. \n\nVancouver's News. Today's Talk. Breaking news & talk radio station.", "created": "2009-01-20 15:12:53+00:00", "followersCount": "112793", "friendsCount": "802", "statusesCount": "221303", "favouritesCount": "2296", "listedCount": "1870", "mediaCount": "17718", "location": "Vancouver, BC", "profileImageUrl": "https://pbs.twimg.com/profile_images/973926520858099712/qK302kKa_normal.jpg", "profileBannerUrl": "https://pbs.twimg.com/profile_banners/19240249/1737475665", "protected": "None", "verified": "False", "blue": "True", "blueType": "Business", "descriptionLinks": [{"url": "http://www.cknw.com", "text": "cknw.com", "tcourl": "https://t.co/XHx9OvsyZM"}], "pinnedIds": "[1881749855695155204]", "_type": "snscrape.modules.twitter_api_client.User"}