{"id": "21110041", "id_str": "21110041", "url": "https://x.com/ctvwinnipeg", "username": "ctvwinnipeg", "displayname": "CTV News Winnipeg", "rawDescription": "The day's top news, plus your Skywatch weather forecast. \nInstagram: https://t.co/8YpoWleZUR\u2026", "created": "2009-02-17 17:44:30+00:00", "followersCount": "169460", "friendsCount": "181", "statusesCount": "207682", "favouritesCount": "159", "listedCount": "809", "mediaCount": "95903", "location": "Winnipeg, Manitoba, Canada", "profileImageUrl": "https://pbs.twimg.com/profile_images/1110208567913656320/IrfLJt4m_normal.png", "profileBannerUrl": "https://pbs.twimg.com/profile_banners/21110041/1500301569", "protected": "None", "verified": "False", "blue": "False", "blueType": "None", "descriptionLinks": [{"url": "http://instagram.com/ctvwinnipeg/?h", "text": "instagram.com/ctvwinnipeg/?h", "tcourl": "https://t.co/8YpoWleZUR"}, {"url": "http://CTVNewsWinnipeg.ca", "text": "CTVNewsWinnipeg.ca", "tcourl": "https://t.co/QVPgAx1O1N"}], "pinnedIds": "[]", "_type": "snscrape.modules.twitter_api_client.User"}