{"id": "990988835336093696", "id_str": "990988835336093696", "url": "https://x.com/FedCourtApp_en", "username": "FedCourtApp_en", "displayname": "Federal Court of Appeal", "rawDescription": "Official Twitter account of the Federal Court of Appeal (Canada). Terms of use: https://t.co/DGf1Mf2CPb Suivez-nous en fran\u00e7ais : @CourAppFed_fr", "created": "2018-04-30 16:18:44+00:00", "followersCount": "3999", "friendsCount": "1", "statusesCount": "274", "favouritesCount": "0", "listedCount": "30", "mediaCount": "31", "location": "", "profileImageUrl": "https://pbs.twimg.com/profile_images/990991071130746881/4IR40iWo_normal.jpg", "profileBannerUrl": "https://pbs.twimg.com/profile_banners/990988835336093696/1688670179", "protected": "None", "verified": "False", "blue": "False", "blueType": "None", "descriptionLinks": [{"url": "http://bit.ly/Twitterterms", "text": "bit.ly/Twitterterms", "tcourl": "https://t.co/DGf1Mf2CPb"}, {"url": "https://www.fca-caf.ca", "text": "fca-caf.ca", "tcourl": "https://t.co/TETyJdliaI"}], "pinnedIds": "[]", "_type": "snscrape.modules.twitter_api_client.User"}