{"id": "32485826", "id_str": "32485826", "url": "https://x.com/FederationCJA", "username": "FederationCJA", "displayname": "Federation CJA", "rawDescription": "Federation CJA is the central philanthropic, planning and coordinating body of services for Montreal\u2019s Jewish community.", "created": "2009-04-17 17:19:02+00:00", "followersCount": "3106", "friendsCount": "613", "statusesCount": "6647", "favouritesCount": "1529", "listedCount": "71", "mediaCount": "2400", "location": "Montreal", "profileImageUrl": "https://pbs.twimg.com/profile_images/1717557114699182080/kBNzPdzh_normal.jpg", "profileBannerUrl": "https://pbs.twimg.com/profile_banners/32485826/1725989367", "protected": "None", "verified": "False", "blue": "False", "blueType": "None", "descriptionLinks": [{"url": "http://www.federationcja.org", "text": "federationcja.org", "tcourl": "https://t.co/FS6g2oDUMv"}], "pinnedIds": "[]", "_type": "snscrape.modules.twitter_api_client.User"}