{"id": "479623622", "id_str": "479623622", "url": "https://x.com/FHCP_PASC", "username": "FHCP_PASC", "displayname": "FHCP / PASC", "rawDescription": "Food, Health & Consumer Products of Canada\nProduits alimentaires, de sant\u00e9 et de consommation du Canada", "created": "2012-01-31 15:50:41+00:00", "followersCount": "3105", "friendsCount": "2274", "statusesCount": "6787", "favouritesCount": "4050", "listedCount": "72", "mediaCount": "2663", "location": "Mississauga, Ontario", "profileImageUrl": "https://pbs.twimg.com/profile_images/1395437081330163727/NuPOb5oY_normal.png", "profileBannerUrl": "https://pbs.twimg.com/profile_banners/479623622/1621532096", "protected": "None", "verified": "False", "blue": "True", "blueType": "None", "descriptionLinks": [{"url": "http://www.fhcp.ca", "text": "fhcp.ca", "tcourl": "https://t.co/eAe4NUDgyV"}], "pinnedIds": "[]", "_type": "snscrape.modules.twitter_api_client.User"}