{"id": "915626667074363393", "id_str": "915626667074363393", "url": "https://x.com/FINTRAC_Canada", "username": "FINTRAC_Canada", "displayname": "FINTRAC_Canada", "rawDescription": "Financial Transactions and Reports Analysis Centre of Canada / En Fran\u00e7ais: @CANAFE_Canada / Notice: https://t.co/zweOEUXOeM", "created": "2017-10-04 17:16:23+00:00", "followersCount": "7186", "friendsCount": "114", "statusesCount": "1874", "favouritesCount": "101", "listedCount": "94", "mediaCount": "735", "location": "Canada", "profileImageUrl": "https://pbs.twimg.com/profile_images/915943626923950081/Lw-QDSiK_normal.jpg", "profileBannerUrl": "https://pbs.twimg.com/profile_banners/915626667074363393/1625493203", "protected": "None", "verified": "False", "blue": "False", "blueType": "Government", "descriptionLinks": [{"url": "http://ow.ly/Qs4O50IiOmG", "text": "ow.ly/Qs4O50IiOmG", "tcourl": "https://t.co/zweOEUXOeM"}, {"url": "https://fintrac-canafe.canada.ca/intro-eng", "text": "fintrac-canafe.canada.ca/intro-eng", "tcourl": "https://t.co/PYXvvQDt58"}], "pinnedIds": "[]", "_type": "snscrape.modules.twitter_api_client.User"}