{"id": "235122381", "id_str": "235122381", "url": "https://x.com/GarnettGenuis", "username": "GarnettGenuis", "displayname": "Garnett Genuis", "rawDescription": "Canadian MP for #shpk #fortsask \u2022 Husband & father \u2022 Politics and human rights \u2022 https://t.co/JHQVyBqCHG", "created": "2011-01-07 12:08:36+00:00", "followersCount": "40634", "friendsCount": "2688", "statusesCount": "10212", "favouritesCount": "1745", "listedCount": "326", "mediaCount": "2524", "location": "Sherwood Park", "profileImageUrl": "https://pbs.twimg.com/profile_images/1715428374225551360/ErvVpnSC_normal.jpg", "profileBannerUrl": "https://pbs.twimg.com/profile_banners/235122381/1622145140", "protected": "None", "verified": "False", "blue": "True", "blueType": "None", "descriptionLinks": [{"url": "https://podcasts.apple.com/ca/podcast/resuming-debate/id1562896468", "text": "podcasts.apple.com/ca/podcast/res\u2026", "tcourl": "https://t.co/JHQVyBqCHG"}, {"url": "https://www.facebook.com/Garnett-Genuis-173928532656310/", "text": "facebook.com/Garnett-Genuis\u2026", "tcourl": "https://t.co/gxaW84fnrw"}], "pinnedIds": "[1851285362817069201]", "_type": "snscrape.modules.twitter_api_client.User"}