{"id": "15193285", "id_str": "15193285", "url": "https://x.com/GreenpeaceCA", "username": "GreenpeaceCA", "displayname": "Greenpeace Canada", "rawDescription": "An independent campaigning organization that uses non-violent, creative confrontation to expose global environmental problems, and to force solutions.", "created": "2008-06-21 23:00:27+00:00", "followersCount": "48701", "friendsCount": "2597", "statusesCount": "32371", "favouritesCount": "37638", "listedCount": "1295", "mediaCount": "7250", "location": "Canada", "profileImageUrl": "https://pbs.twimg.com/profile_images/1116345750026321927/SIlATau2_normal.png", "profileBannerUrl": "https://pbs.twimg.com/profile_banners/15193285/1684341443", "protected": "None", "verified": "False", "blue": "False", "blueType": "None", "descriptionLinks": [{"url": "http://greenpeace.ca", "text": "greenpeace.ca", "tcourl": "https://t.co/uIUjCxao2x"}], "pinnedIds": "[]", "_type": "snscrape.modules.twitter_api_client.User"}