{"id": "89265769", "id_str": "89265769", "url": "https://x.com/ianabailey", "username": "ianabailey", "displayname": "Ian Bailey", "rawDescription": "Ottawa -based Globe & Mail reporter.  Retweets do not equal endorsements.", "created": "2009-11-11 19:50:05+00:00", "followersCount": "13841", "friendsCount": "6667", "statusesCount": "197019", "favouritesCount": "7153", "listedCount": "535", "mediaCount": "3217", "location": "Ottawa, Ontario", "profileImageUrl": "https://pbs.twimg.com/profile_images/996894725696241664/Ks9aKkCL_normal.jpg", "profileBannerUrl": "None", "protected": "None", "verified": "False", "blue": "False", "blueType": "None", "descriptionLinks": [{"url": "http://www.theglobeandmail.com/authors/ian-bailey", "text": "theglobeandmail.com/authors/ian-ba\u2026", "tcourl": "https://t.co/2gFZT0lIUT"}], "pinnedIds": "[]", "_type": "snscrape.modules.twitter_api_client.User"}