{"id": "1416049134", "id_str": "1416049134", "url": "https://x.com/Jeff__yates", "username": "Jeff__yates", "displayname": "Jeff Yates", "rawDescription": "Journaliste \u00e0 Radio-Canada, D\u00e9crypteurs. Je gosse les gens avec les fausses nouvelles depuis 2014. Parfois barbu. Peut-\u00eatre un l\u00e9zard.", "created": "2013-05-09 17:37:35+00:00", "followersCount": "18840", "friendsCount": "1824", "statusesCount": "8559", "favouritesCount": "5305", "listedCount": "186", "mediaCount": "1614", "location": "Montreal", "profileImageUrl": "https://pbs.twimg.com/profile_images/1129388900521304065/tpIOlF4y_normal.png", "profileBannerUrl": "https://pbs.twimg.com/profile_banners/1416049134/1687377178", "protected": "None", "verified": "False", "blue": "False", "blueType": "None", "descriptionLinks": [{"url": "http://radio-canada.ca/decrypteurs", "text": "radio-canada.ca/decrypteurs", "tcourl": "https://t.co/I1eSS90wmr"}], "pinnedIds": "[1831083673812439520]", "_type": "snscrape.modules.twitter_api_client.User"}