{"id": "19714882", "id_str": "19714882", "url": "https://x.com/jenniferhollett", "username": "jenniferhollett", "displayname": "Jennifer Hollett", "rawDescription": "Media, tech, & politics. Executive Director @TheWalrus Before that, news/gov @Twitter On here, wondering why I'm on here. Also: https://t.co/ic6hjIMYRx", "created": "2009-01-29 15:16:17+00:00", "followersCount": "17530", "friendsCount": "5923", "statusesCount": "35284", "favouritesCount": "12961", "listedCount": "438", "mediaCount": "3416", "location": "Toronto", "profileImageUrl": "https://pbs.twimg.com/profile_images/1556772764991750145/cCsbPaEg_normal.jpg", "profileBannerUrl": "https://pbs.twimg.com/profile_banners/19714882/1714167287", "protected": "None", "verified": "False", "blue": "False", "blueType": "None", "descriptionLinks": [{"url": "http://jenniferhollett.bsky.social", "text": "jenniferhollett.bsky.social", "tcourl": "https://t.co/ic6hjIMYRx"}, {"url": "http://www.jenniferhollett.com", "text": "jenniferhollett.com", "tcourl": "https://t.co/COVFUI9pa5"}], "pinnedIds": "[]", "_type": "snscrape.modules.twitter_api_client.User"}