{"id": "1076144373132378112", "id_str": "1076144373132378112", "url": "https://x.com/JJulienCAQ", "username": "JJulienCAQ", "displayname": "Jonatan Julien", "rawDescription": "D\u00e9put\u00e9 de Charlesbourg, ministre responsable des Infrastructures et ministre responsable de la r\u00e9gion de la Capitale-Nationale", "created": "2018-12-21 15:56:27+00:00", "followersCount": "4342", "friendsCount": "298", "statusesCount": "1765", "favouritesCount": "779", "listedCount": "72", "mediaCount": "434", "location": "Qu\u00e9bec, Canada", "profileImageUrl": "https://pbs.twimg.com/profile_images/1597684232855457792/7V9dKI7d_normal.jpg", "profileBannerUrl": "https://pbs.twimg.com/profile_banners/1076144373132378112/1661712474", "protected": "None", "verified": "False", "blue": "False", "blueType": "None", "descriptionLinks": [{"url": "http://www.assnat.qc.ca/fr/deputes/julien-jonatan-17855/index.html?appelant=MC", "text": "assnat.qc.ca/fr/deputes/jul\u2026", "tcourl": "https://t.co/KDOa0kci1f"}], "pinnedIds": "[]", "_type": "snscrape.modules.twitter_api_client.User"}