{"id": "425118862", "id_str": "425118862", "url": "https://x.com/KitchLibrary", "username": "KitchLibrary", "displayname": "Kitchener Public Library", "rawDescription": "To inspire and enrich for life.", "created": "2011-11-30 15:47:15+00:00", "followersCount": "12746", "friendsCount": "2677", "statusesCount": "29613", "favouritesCount": "10905", "listedCount": "285", "mediaCount": "6410", "location": "Kitchener, Ontario, Canada", "profileImageUrl": "https://pbs.twimg.com/profile_images/1583456423152844801/MBLOYo0q_normal.jpg", "profileBannerUrl": "https://pbs.twimg.com/profile_banners/425118862/1666360406", "protected": "None", "verified": "False", "blue": "False", "blueType": "None", "descriptionLinks": [{"url": "http://kpl.org", "text": "kpl.org", "tcourl": "https://t.co/6NMjNFbzEF"}], "pinnedIds": "[]", "_type": "snscrape.modules.twitter_api_client.User"}