{"id": "235717819", "id_str": "235717819", "url": "https://x.com/KNugent4118", "username": "KNugent4118", "displayname": "KNugent4118 \ud83c\udde8\ud83c\udde6\ud83c\udde8\ud83c\udde6\ud83c\udde8\ud83c\udde6", "rawDescription": "I am a proud Canadian  Liberal because I believe in progress and democracy. Conservatives want to destroy both. \n#Democrat\n#prochoice\nhttps://t.co/RXRugrGrqr", "created": "2011-01-08 22:50:53+00:00", "followersCount": "15265", "friendsCount": "7930", "statusesCount": "71493", "favouritesCount": "310002", "listedCount": "2", "mediaCount": "15772", "location": "Ontario, Canada", "profileImageUrl": "https://pbs.twimg.com/profile_images/1812875654150365185/SBjoUSBU_normal.jpg", "profileBannerUrl": "https://pbs.twimg.com/profile_banners/235717819/1568675232", "protected": "None", "verified": "False", "blue": "False", "blueType": "None", "descriptionLinks": [{"url": "http://knugent4118.bsky.so", "text": "knugent4118.bsky.so", "tcourl": "https://t.co/RXRugrGrqr"}], "pinnedIds": "[1857092343490359577]", "_type": "snscrape.modules.twitter_api_client.User"}