{"id": "2986505901", "id_str": "2986505901", "url": "https://x.com/LaframboiseMa", "username": "LaframboiseMa", "displayname": "Mario Laframboise", "rawDescription": "Whip en chef du gouvernement et D\u00e9put\u00e9 de Blainville", "created": "2015-01-19 23:22:30+00:00", "followersCount": "2823", "friendsCount": "240", "statusesCount": "516", "favouritesCount": "138", "listedCount": "76", "mediaCount": "219", "location": "Blainville, Qu\u00e9bec", "profileImageUrl": "https://pbs.twimg.com/profile_images/1563906682203394048/8QnlX3s-_normal.jpg", "profileBannerUrl": "https://pbs.twimg.com/profile_banners/2986505901/1661699415", "protected": "None", "verified": "False", "blue": "False", "blueType": "None", "descriptionLinks": [{"url": "http://mario-laframboise.com", "text": "mario-laframboise.com", "tcourl": "https://t.co/NFES87jzB1"}], "pinnedIds": "[]", "_type": "snscrape.modules.twitter_api_client.User"}