{"id": "401451204", "id_str": "401451204", "url": "https://x.com/LeducAlexandre", "username": "LeducAlexandre", "displayname": "Alexandre Leduc", "rawDescription": "D\u00e9put\u00e9 solidaire de Hochelaga-Maisonneuve. Leader parlementaire. Historien de formation, syndicaliste et papa enthousiaste.", "created": "2011-10-30 15:26:55+00:00", "followersCount": "7111", "friendsCount": "3635", "statusesCount": "5041", "favouritesCount": "943", "listedCount": "141", "mediaCount": "475", "location": "Montr\u00e9al", "profileImageUrl": "https://pbs.twimg.com/profile_images/1483544459816185857/_klf7IYG_normal.jpg", "profileBannerUrl": "https://pbs.twimg.com/profile_banners/401451204/1643823475", "protected": "None", "verified": "False", "blue": "False", "blueType": "None", "descriptionLinks": [{"url": "https://www.facebook.com/LeducAlexandreQS/", "text": "facebook.com/LeducAlexandre\u2026", "tcourl": "https://t.co/N4AtXuGTAI"}], "pinnedIds": "[]", "_type": "snscrape.modules.twitter_api_client.User"}