{"id": "409766321", "id_str": "409766321", "url": "https://x.com/MichaelParsa", "username": "MichaelParsa", "displayname": "Michael Parsa", "rawDescription": "@OntarioPCParty Candidate for Aurora\u2014Oak Ridges\u2014Richmond Hill\n#AuroraOakRidgesRichmondHill", "created": "2011-11-11 05:53:56+00:00", "followersCount": "7400", "friendsCount": "1680", "statusesCount": "6269", "favouritesCount": "27314", "listedCount": "116", "mediaCount": "3312", "location": "Richmond Hill, Ontario", "profileImageUrl": "https://pbs.twimg.com/profile_images/1464927818656231429/S8v8dsaf_normal.jpg", "profileBannerUrl": "https://pbs.twimg.com/profile_banners/409766321/1738126998", "protected": "None", "verified": "False", "blue": "True", "blueType": "Government", "descriptionLinks": [{"url": "https://michaelparsa.ca", "text": "michaelparsa.ca", "tcourl": "https://t.co/mXBZaWn1Ti"}], "pinnedIds": "[]", "_type": "snscrape.modules.twitter_api_client.User"}