{"id": "169153552", "id_str": "169153552", "url": "https://x.com/moose995", "username": "moose995", "displayname": "99.5 Moose FM", "rawDescription": "MUSKOKA'S BEST MUSIC! Home of Moose Mornings with Remy and Afternoons with Michelle!", "created": "2010-07-21 17:38:33+00:00", "followersCount": "7220", "friendsCount": "1308", "statusesCount": "26342", "favouritesCount": "1271", "listedCount": "69", "mediaCount": "3403", "location": "Bracebridge, Ontario", "profileImageUrl": "https://pbs.twimg.com/profile_images/1740028281838006273/LZ5ovx82_normal.jpg", "profileBannerUrl": "https://pbs.twimg.com/profile_banners/169153552/1704399470", "protected": "None", "verified": "False", "blue": "False", "blueType": "None", "descriptionLinks": [{"url": "https://www.mymuskokanow.com/", "text": "mymuskokanow.com", "tcourl": "https://t.co/yP6c6eK3G3"}], "pinnedIds": "[]", "_type": "snscrape.modules.twitter_api_client.User"}