{"id": "14695028", "id_str": "14695028", "url": "https://x.com/morricemike", "username": "morricemike", "displayname": "Mike Morrice", "rawDescription": "Member of Parliament for Kitchener Centre, @CanadianGreens. Founder @SustainableWat and @GreenEconomyCa. He/him.\nEmail: mike.morrice.C1@parl.gc.ca", "created": "2008-05-08 02:21:45+00:00", "followersCount": "13158", "friendsCount": "4248", "statusesCount": "5249", "favouritesCount": "16951", "listedCount": "137", "mediaCount": "1259", "location": "Block 2, Haldimand Tract", "profileImageUrl": "https://pbs.twimg.com/profile_images/1417880279625224198/vGVAtUrc_normal.jpg", "profileBannerUrl": "https://pbs.twimg.com/profile_banners/14695028/1635350490", "protected": "None", "verified": "False", "blue": "False", "blueType": "None", "descriptionLinks": [{"url": "http://www.mikemorricemp.ca", "text": "mikemorricemp.ca", "tcourl": "https://t.co/brFOx7M1GE"}], "pinnedIds": "[1882157097900765412]", "_type": "snscrape.modules.twitter_api_client.User"}