{"id": "380680185", "id_str": "380680185", "url": "https://x.com/Muskoka411", "username": "Muskoka411", "displayname": "Muskoka411 News", "rawDescription": "News organization providing the best in breaking news, traffic, weather and more for Muskoka and the surrounding areas. Tweet us your photos and news tips.", "created": "2011-09-27 01:50:10+00:00", "followersCount": "31411", "friendsCount": "9468", "statusesCount": "136026", "favouritesCount": "99706", "listedCount": "287", "mediaCount": "22607", "location": "Muskoka, Ontario", "profileImageUrl": "https://pbs.twimg.com/profile_images/1807801228450992128/kwOkf_O__normal.jpg", "profileBannerUrl": "https://pbs.twimg.com/profile_banners/380680185/1662903738", "protected": "None", "verified": "False", "blue": "True", "blueType": "None", "descriptionLinks": [{"url": "http://www.muskoka411.com", "text": "muskoka411.com", "tcourl": "https://t.co/U336C9spnk"}], "pinnedIds": "[1883986922642493815]", "_type": "snscrape.modules.twitter_api_client.User"}