{"id": "1298269898708119553", "id_str": "1298269898708119553", "url": "https://x.com/OMNIFilipino", "username": "OMNIFilipino", "displayname": "OMNI Filipino", "rawDescription": "This is the home of stories about/for Filipinos and Filipino-Canadians. Every night at 8 p.m. ET/PT on @OMNITelevision \ud83c\uddf5\ud83c\udded", "created": "2020-08-25 14:45:32+00:00", "followersCount": "1313", "friendsCount": "38", "statusesCount": "1364", "favouritesCount": "1285", "listedCount": "10", "mediaCount": "196", "location": "Canada", "profileImageUrl": "https://pbs.twimg.com/profile_images/1298270620367458311/siRdBDZ1_normal.jpg", "profileBannerUrl": "https://pbs.twimg.com/profile_banners/1298269898708119553/1598366843", "protected": "None", "verified": "False", "blue": "False", "blueType": "None", "descriptionLinks": [{"url": "http://omnitv.ca", "text": "omnitv.ca", "tcourl": "https://t.co/fq933Uwebf"}], "pinnedIds": "[]", "_type": "snscrape.modules.twitter_api_client.User"}