{"id": "1506401373293891593", "id_str": "1506401373293891593", "url": "https://x.com/S_A_M_CDN", "username": "S_A_M_CDN", "displayname": "Students Against Mandates", "rawDescription": "Non-profit, non-partisan organization committed to eliminating University Covid-19 mandates. 'The SAM Podcast' is on Rumble, Youtube, Apple & Spotify podcasts.", "created": "2022-03-22 22:44:59+00:00", "followersCount": "6486", "friendsCount": "1346", "statusesCount": "1643", "favouritesCount": "14013", "listedCount": "22", "mediaCount": "96", "location": "Canada", "profileImageUrl": "https://pbs.twimg.com/profile_images/1506412301045440516/gKfyvjlG_normal.jpg", "profileBannerUrl": "https://pbs.twimg.com/profile_banners/1506401373293891593/1670471150", "protected": "None", "verified": "False", "blue": "False", "blueType": "None", "descriptionLinks": [{"url": "https://linktr.ee/students_against_mandates", "text": "linktr.ee/students_again\u2026", "tcourl": "https://t.co/LdBr0p4FqS"}], "pinnedIds": "[1778934640088334420]", "_type": "snscrape.modules.twitter_api_client.User"}