{"id": "1305950751320150016", "id_str": "1305950751320150016", "url": "https://x.com/SandeeLovas", "username": "SandeeLovas", "displayname": "Left of the Box - Sandee\ud83d\udc9b\ud83e\udd0d\ud83d\udc9c\ud83d\udda4", "rawDescription": "Canadian politics with sarcasm and sass.  (NB - She/Her, Mr/Sir, Folk, They/Them) also follow @LeftOfTheBox See my art https://t.co/JEPL5mM5Zh", "created": "2020-09-15 19:25:08+00:00", "followersCount": "2219", "friendsCount": "761", "statusesCount": "10019", "favouritesCount": "46562", "listedCount": "10", "mediaCount": "2077", "location": "Ontario", "profileImageUrl": "https://pbs.twimg.com/profile_images/1855675526947491840/WHsvSPPQ_normal.jpg", "profileBannerUrl": "https://pbs.twimg.com/profile_banners/1305950751320150016/1730655928", "protected": "None", "verified": "False", "blue": "False", "blueType": "None", "descriptionLinks": [{"url": "http://www.sandeelovas.com", "text": "sandeelovas.com", "tcourl": "https://t.co/JEPL5mM5Zh"}, {"url": "https://www.youtube.com/c/leftofthebox", "text": "youtube.com/c/leftofthebox", "tcourl": "https://t.co/cPtD9AEv8j"}], "pinnedIds": "[1857170890644959719]", "_type": "snscrape.modules.twitter_api_client.User"}