{"id": "398752046", "id_str": "398752046", "url": "https://x.com/StewGlobal", "username": "StewGlobal", "displayname": "Stewart Bell", "rawDescription": "Investigative journalist at Global News. https://t.co/70QV4okxDx\u2026 MultiPlatformContentProvider. @ConBlackSabbath Bassist Stewart.Bell@globalnews.ca", "created": "2011-10-26 14:04:43+00:00", "followersCount": "12228", "friendsCount": "2958", "statusesCount": "24091", "favouritesCount": "4376", "listedCount": "236", "mediaCount": "3739", "location": "West of Toronto", "profileImageUrl": "https://pbs.twimg.com/profile_images/1219327549198782464/w9Iy5hio_normal.jpg", "profileBannerUrl": "https://pbs.twimg.com/profile_banners/398752046/1660084864", "protected": "None", "verified": "False", "blue": "False", "blueType": "None", "descriptionLinks": [{"url": "http://globalnews.ca/author/stewart", "text": "globalnews.ca/author/stewart", "tcourl": "https://t.co/70QV4okxDx"}, {"url": "https://www.harpercollins.com/blogs/authors/stewart-bell", "text": "harpercollins.com/blogs/authors/\u2026", "tcourl": "https://t.co/OnIXqglEJn"}], "pinnedIds": "[1894375440875491693]", "_type": "snscrape.modules.twitter_api_client.User"}