{"id": "997123216471506944", "id_str": "997123216471506944", "url": "https://x.com/taoist_canada", "username": "taoist_canada", "displayname": "Fung Loy Kok Taoist Tai Chi\u00ae", "rawDescription": "Taoist Tai Chi\u00ae arts are Taoist training to bring harmony & balance to body, mind & heart. They include Taoist Tai Chi\u00ae practice, meditation and chanting.", "created": "2018-05-17 14:34:35+00:00", "followersCount": "843", "friendsCount": "8", "statusesCount": "949", "favouritesCount": "188", "listedCount": "11", "mediaCount": "843", "location": "Canada", "profileImageUrl": "https://pbs.twimg.com/profile_images/1589621830008061957/MDrjiQb2_normal.jpg", "profileBannerUrl": "https://pbs.twimg.com/profile_banners/997123216471506944/1724850281", "protected": "None", "verified": "False", "blue": "False", "blueType": "None", "descriptionLinks": [{"url": "http://www.taoist.org", "text": "taoist.org", "tcourl": "https://t.co/b3C4eQrZzK"}], "pinnedIds": "[]", "_type": "snscrape.modules.twitter_api_client.User"}