{"id": "3385326313", "id_str": "3385326313", "url": "https://x.com/TGCFandFriends", "username": "TGCFandFriends", "displayname": "The Great Commission Foundation", "rawDescription": "\u2014The Great Commission Foundation\u2014provides financial management services for the people who serve the world.", "created": "2015-08-29 20:39:05+00:00", "followersCount": "415", "friendsCount": "1146", "statusesCount": "1387", "favouritesCount": "33", "listedCount": "6", "mediaCount": "443", "location": "Canada", "profileImageUrl": "https://pbs.twimg.com/profile_images/1783242353181929472/JLByLr5Y_normal.jpg", "profileBannerUrl": "https://pbs.twimg.com/profile_banners/3385326313/1486145900", "protected": "None", "verified": "False", "blue": "False", "blueType": "None", "descriptionLinks": [{"url": "http://gcfcanada.com", "text": "gcfcanada.com", "tcourl": "https://t.co/MkkOOD5Hs5"}], "pinnedIds": "[]", "_type": "snscrape.modules.twitter_api_client.User"}