{"id": "1090146679695626241", "id_str": "1090146679695626241", "url": "https://x.com/Women___Exist", "username": "Women___Exist", "displayname": "\ud83c\udde8\ud83c\udde6 Women Exist \u2640", "rawDescription": "Pamela, a woman: #AdultHumanFemale. Woman-centred. Stop anti-scientific, homophobic gender propaganda.Warning:I use evidence. Agent 4567.  #HoldTheLine", "created": "2019-01-29 07:16:37+00:00", "followersCount": "29475", "friendsCount": "5118", "statusesCount": "192468", "favouritesCount": "388304", "listedCount": "121", "mediaCount": "22533", "location": "", "profileImageUrl": "https://pbs.twimg.com/profile_images/1849489840624287745/s19Zugwk_normal.jpg", "profileBannerUrl": "https://pbs.twimg.com/profile_banners/1090146679695626241/1729786197", "protected": "None", "verified": "False", "blue": "True", "blueType": "None", "descriptionLinks": [], "pinnedIds": "[1226765127304630272]", "_type": "snscrape.modules.twitter_api_client.User"}